LICENSE
MANIFEST.in
depot_downloader-win32.spec
depot_downloader.py
depot_downloader.spec
requirements.pip
setup.py
pysteamkit/__init__.py
pysteamkit/cdn_client_pool.py
pysteamkit/crypto.py
pysteamkit/depot_manifest.py
pysteamkit/steam_base.py
pysteamkit/steamid.py
pysteamkit/util.py
pysteamkit/vdf.py
pysteamkit.egg-info/PKG-INFO
pysteamkit.egg-info/SOURCES.txt
pysteamkit.egg-info/dependency_links.txt
pysteamkit.egg-info/top_level.txt
pysteamkit/protobuf/__init__.py
pysteamkit/protobuf/content_manifest_pb2.py
pysteamkit/protobuf/encrypted_app_ticket_pb2.py
pysteamkit/protobuf/steammessages_base_pb2.py
pysteamkit/protobuf/steammessages_clientserver_pb2.py
pysteamkit/steam3/__init__.py
pysteamkit/steam3/cdn_client.py
pysteamkit/steam3/client.py
pysteamkit/steam3/connection.py
pysteamkit/steam3/msg_base.py
pysteamkit/steam3/steamapps.py