Metadata-Version: 1.1
Name: pysteamkit
Version: 0.0.1
Summary: A library for working with Steam
Home-page: https://bitbucket.org/AzuiSleet/pysteamkit
Author: Ryan Kistner
Author-email: azuisleet@gmail.com
License: UNKNOWN
Keywords: steam pysteamkit
Platform: UNKNOWN
Classifier: Development Status :: 3 - Alpha
Classifier: Topic :: Internet
